ormsgpack-1.8.0.dist-info/METADATA
ormsgpack-1.8.0.dist-info/WHEEL
ormsgpack-1.8.0.dist-info/licenses/LICENSE-APACHE
ormsgpack-1.8.0.dist-info/licenses/LICENSE-MIT
ormsgpack/py.typed
ormsgpack/__init__.py
ormsgpack/__init__.pyi
ormsgpack/ormsgpack.cp311-win_amd64.pyd
ormsgpack-1.8.0.dist-info/RECORD
