Metadata-Version: 2.4
Name: ormsgpack
Version: 1.8.0
Classifier: Development Status :: 5 - Production/Stable
Classifier: Intended Audience :: Developers
Classifier: License :: OSI Approved :: Apache Software License
Classifier: License :: OSI Approved :: MIT License
Classifier: Operating System :: MacOS
Classifier: Operating System :: Microsoft :: Windows
Classifier: Operating System :: POSIX :: Linux
Classifier: Programming Language :: Python :: 3
Classifier: Programming Language :: Python :: 3.9
Classifier: Programming Language :: Python :: 3.10
Classifier: Programming Language :: Python :: 3.11
Classifier: Programming Language :: Python :: 3.12
Classifier: Programming Language :: Python :: 3.13
Classifier: Programming Language :: Python :: Implementation :: CPython
Classifier: Programming Language :: Python
Classifier: Programming Language :: Rust
Classifier: Typing :: Typed
License-File: LICENSE-APACHE
License-File: LICENSE-MIT
Summary: Fast, correct Python msgpack library supporting dataclasses, datetimes, and numpy
Keywords: fast,msgpack,dataclass,dataclasses,datetime
Home-Page: https://github.com/aviramha/ormsgpack
Author: Aviram Hassan <aviramyhassan@gmail.com>, Emanuele Giaquinta <emanuele.giaquinta@gmail.com>
Author-email: Aviram Hassan <aviramyhassan@gmail.com>, Emanuele Giaquinta <emanuele.giaquinta@gmail.com>
License: Apache-2.0 OR MIT
Requires-Python: >=3.9
Project-URL: Source Code, https://github.com/aviramha/ormsgpack
